niktokenizer/__init__.py
niktokenizer/tokenizer.py
niktokenizer-0.1.0.dist-info/licenses/LICENSE
niktokenizer-0.1.0.dist-info/METADATA
niktokenizer-0.1.0.dist-info/WHEEL
niktokenizer-0.1.0.dist-info/top_level.txt
niktokenizer-0.1.0.dist-info/RECORD
